{"note":"This file is an internal implementation detail to speed up HTML report generation. Its format can change at any time. You might be looking for the JSON report: https://coverage.rtfd.io/cmd.html#cmd-json","format":5,"version":"7.7.0","globals":"c3a7e2dc0786ebec7102f7e6b043c79f","files":{"__init___py":{"hash":"e6baa73cda2916dad605215f937a92e1","index":{"url":"__init___py.html","file":"__init__.py","description":"","nums":{"precision":0,"n_files":1,"n_statements":0,"n_excluded":0,"n_missing":0,"n_branches":0,"n_partial_branches":0,"n_missing_branches":0}}},"app_py":{"hash":"a5870b60dee4118baa48bdee1bb9a72c","index":{"url":"app_py.html","file":"app.py","description":"","nums":{"precision":0,"n_files":1,"n_statements":32,"n_excluded":0,"n_missing":0,"n_branches":0,"n_partial_branches":0,"n_missing_branches":0}}},"test_app_py":{"hash":"71c51d44322acf410f48c23ac0c8f255","index":{"url":"test_app_py.html","file":"test_app.py","description":"","nums":{"precision":0,"n_files":1,"n_statements":85,"n_excluded":0,"n_missing":0,"n_branches":0,"n_partial_branches":0,"n_missing_branches":0}}}}}